airfrans/__init__.py
airfrans/dataset.py
airfrans/naca_generator.py
airfrans/reorganize.py
airfrans/sampling.py
airfrans/simulation.py
airfrans-0.1.5.1.dist-info/METADATA
airfrans-0.1.5.1.dist-info/WHEEL
airfrans-0.1.5.1.dist-info/licenses/LICENSE
airfrans-0.1.5.1.dist-info/RECORD
