Metadata-Version: 2.1
Name: airfrans
Version: 0.1.5.1
Summary: A package to facilitate the manipulation of the AirfRANS dataset simulations.
Project-URL: Homepage, https://github.com/Extrality/airfrans_lib
Project-URL: Bug Tracker, https://github.com/Extrality/airfrans_lib/issues
Author-email: Florent Bonnet <bonnet@isir.upmc.fr>
License-File: LICENSE
Classifier: License :: OSI Approved :: MIT License
Classifier: Operating System :: OS Independent
Classifier: Programming Language :: Python :: 3
Classifier: Topic :: Scientific/Engineering :: Artificial Intelligence
Classifier: Topic :: Scientific/Engineering :: Physics
Requires-Python: >=3.7
Requires-Dist: numpy
Requires-Dist: pyvista>=0.37.0
Requires-Dist: tqdm
